gpx_csv_converter/__init__.py
gpx_csv_converter-0.2.2.dist-info/LICENSE
gpx_csv_converter-0.2.2.dist-info/METADATA
gpx_csv_converter-0.2.2.dist-info/WHEEL
gpx_csv_converter-0.2.2.dist-info/top_level.txt
gpx_csv_converter-0.2.2.dist-info/RECORD
