Metadata-Version: 2.1
Name: gpx-csv-converter
Version: 0.2.2
Summary: An easy way to convert between GPX and CSV files
Home-page: https://github.com/ethanzh/gpx-csv-converter
Author: Ethan Houston
Author-email: ethan.houston@gmail.com
License: UNKNOWN
Platform: UNKNOWN
Classifier: Programming Language :: Python :: 3
Classifier: License :: OSI Approved :: MIT License
Classifier: Operating System :: OS Independent
